datapick/__init__.py
datapick/backends.py
datapick/definitions.py
datapick/logic.py
datapick/utils.py
datapick-0.0.1.dist-info/METADATA
datapick-0.0.1.dist-info/WHEEL
datapick-0.0.1.dist-info/RECORD
