Metadata-Version: 2.3
Name: datapick
Version: 0.0.1
Summary: The official datapick SDK for Python
Author-email: Datapick Engineering <engineering@datapick.ai>
Requires-Dist: anthropic==0.25.6
Requires-Dist: groq==0.5.0
Requires-Dist: openai==1.16.2
Requires-Dist: pydantic==2.6.4
Requires-Dist: pypdf2==3.0.1
Requires-Dist: python-dotenv==1.0.1
Requires-Dist: requests==2.31.0
Requires-Dist: typing-extensions==4.11.0
